vump_grpc_client/__init__.py
vump_grpc_client/api_services/__init__.py
vump_grpc_client/api_services/_base.py
vump_grpc_client/api_services/handler/__init__.py
vump_grpc_client/api_services/handler/add_client.py
vump_grpc_client/api_services/handler/remove_client.py
vump_grpc_client/api_services/logger/__init__.py
vump_grpc_client/api_services/logger/restart_logger.py
vump_grpc_client/api_services/stats/__init__.py
vump_grpc_client/api_services/stats/get_client_download_traffic.py
vump_grpc_client/api_services/stats/get_client_upload_traffic.py
vump_grpc_client/api_services/stats/get_inbound_download_traffic.py
vump_grpc_client/api_services/stats/get_inbound_upload_traffic.py
vump_grpc_client/api_services/stats/get_total_download_traffic.py
vump_grpc_client/api_services/stats/get_total_upload_traffic.py
vump_grpc_client/client/__init__.py
vump_grpc_client/client/vump.py
vump_grpc_client/exceptions/__init__.py
vump_grpc_client/exceptions/_base.py
vump_grpc_client/exceptions/email_already_exists.py
vump_grpc_client/exceptions/email_not_found.py
vump_grpc_client/exceptions/inbound_not_found.py
vump_grpc_client/ext/__init__.py
vump_grpc_client/ext/utils.py
vump_grpc_client/v2ray_api/__init__.py
vump_grpc_client/v2ray_api/config_pb2.py
vump_grpc_client/v2ray_api/config_pb2_grpc.py
vump_grpc_client/v2ray_api/app/__init__.py
vump_grpc_client/v2ray_api/app/commander/__init__.py
vump_grpc_client/v2ray_api/app/commander/config_pb2.py
vump_grpc_client/v2ray_api/app/commander/config_pb2_grpc.py
vump_grpc_client/v2ray_api/app/dispatcher/__init__.py
vump_grpc_client/v2ray_api/app/dispatcher/config_pb2.py
vump_grpc_client/v2ray_api/app/dispatcher/config_pb2_grpc.py
vump_grpc_client/v2ray_api/app/dns/__init__.py
vump_grpc_client/v2ray_api/app/dns/config_pb2.py
vump_grpc_client/v2ray_api/app/dns/config_pb2_grpc.py
vump_grpc_client/v2ray_api/app/log/__init__.py
vump_grpc_client/v2ray_api/app/log/config_pb2.py
vump_grpc_client/v2ray_api/app/log/config_pb2_grpc.py
VUMP_gRPC_client-1.0.2.dist-info/LICENSE
VUMP_gRPC_client-1.0.2.dist-info/METADATA
VUMP_gRPC_client-1.0.2.dist-info/WHEEL
VUMP_gRPC_client-1.0.2.dist-info/top_level.txt
VUMP_gRPC_client-1.0.2.dist-info/RECORD
