Metadata-Version: 2.1
Name: VUMP-gRPC-client
Version: 1.0.2
Summary: a python gRPC client for V2Ray/V2Fly gRPC API
Home-page: https://github.com/V2ray-UMP/VUMP-gRPC-client
Author: V2ray-UMP
Author-email: a@b.c
License: MIT License (MIT)
Project-URL: API Docs Reference, https://www.v2fly.org/config/api.html#apiobject
Project-URL: Discussions, https://github.com/V2ray-UMP/VUMP-gRPC-client/discussions
Project-URL: Issues, https://github.com/V2ray-UMP/VUMP-gRPC-client/issues
Keywords: v2ray grpc python client
Classifier: Topic :: Software Development :: Libraries
Classifier: Topic :: Software Development :: Libraries :: Python Modules
Classifier: Programming Language :: Python :: Implementation :: CPython
Classifier: Programming Language :: Python :: 3.10
Classifier: Programming Language :: Python :: 3
Classifier: Programming Language :: Python
Classifier: License :: OSI Approved :: MIT License
Classifier: Development Status :: 3 - Alpha
Requires-Python: >=3.9.0
License-File: LICENSE
Requires-Dist: grpcio (==1.50)
Requires-Dist: grpcio-tools (==1.50)
